<?xml version="1.0" encoding="utf-8"?>
<odoo>
    <record model="ir.ui.view" id="view_account_payment_term_type">
        <field name="name">view.account.payment.term.type</field>
        <field name="model">account.payment.term</field>
        <field name="inherit_id" ref="account.view_payment_term_form"/>
        <field name="arch" type="xml">
            <xpath expr="//field[@name='active']" position="after">
                <newline/>
                <field name="payment_type"/>
            </xpath>
        </field>
    </record>

    <record id="view_res_config_settings_payment_type" model="ir.ui.view">
        <field name="name">res.config.setting.payment.type</field>
        <field name="model">res.config.settings</field>
        <field name="inherit_id" ref="account.res_config_settings_view_form"/>
        <field name="arch" type="xml">
            <div id="account_followup" position="after">
               <div class="col-xs-12 col-md-6 o_setting_box">
                    <div class="o_setting_right_pane">
                        <label for="payment_type"/>
                        <div class="content-group">
                            <div class="mt16">
                                <field name="payment_type"/>
                            </div>
                        </div>
                    </div>
                </div>
            </div>
        </field>
    </record>
</odoo>
